{
  "_note": "Curated Open5e reskins for post-apocalyptic. Wasteland renames over real stat blocks; cr denormalized and verified by scripts/test-bestiary.mjs.",
  "entries": [
    { "slug": "giant-rat", "name": "Rad-Rat", "cr": 0.125, "blurb": "glow-eyed vermin of the ruin fields" },
    { "slug": "bandit", "name": "Road Raider", "cr": 0.125, "blurb": "scrap-armored highway predator" },
    { "slug": "kobold", "name": "Tunnel Scav", "cr": 0.125, "blurb": "trap-happy dweller of the metro dark" },
    { "slug": "cultist", "name": "Doomsayer", "cr": 0.125, "blurb": "preaches the Fall was only the beginning" },
    { "slug": "stirge", "name": "Blood Wasp", "cr": 0.125, "blurb": "mutant bloodsucker from the swamp glass" },
    { "slug": "poisonous-snake", "name": "Glass Viper", "cr": 0.125, "blurb": "iridescent serpent of the fused sands" },
    { "slug": "zombie", "name": "Rad-Feral", "cr": 0.25, "blurb": "burned husk that still remembers hunger" },
    { "slug": "skeleton", "name": "Ash Walker", "cr": 0.25, "blurb": "bones fused with rebar and wire" },
    { "slug": "goblin", "name": "Junkyard Imp", "cr": 0.25, "blurb": "small, fast, armed with sharpened scrap" },
    { "slug": "wolf", "name": "Waste Hound", "cr": 0.25, "blurb": "lean pack hunter of the dead highways" },
    { "slug": "giant-centipede", "name": "Pipe Crawler", "cr": 0.25, "blurb": "venomous meter-long conduit dweller" },
    { "slug": "acolyte", "name": "Shelter Medic", "cr": 0.25, "blurb": "vault-trained healer with old-world tricks" },
    { "slug": "thug", "name": "Warlord's Enforcer", "cr": 0.5, "blurb": "collects the water tax with a pipe wrench" },
    { "slug": "orc", "name": "Crater Brute", "cr": 0.5, "blurb": "mutation-swollen shock raider" },
    { "slug": "gnoll", "name": "Howler", "cr": 0.5, "blurb": "cackling cannibal of the dust plains" },
    { "slug": "hobgoblin", "name": "Junta Trooper", "cr": 0.5, "blurb": "uniformed remnant of the old army" },
    { "slug": "shadow", "name": "Fallout Shade", "cr": 0.5, "blurb": "burned silhouette peeled off a wall" },
    { "slug": "rust-monster", "name": "Oxide Beast", "cr": 0.5, "blurb": "eats guns, armor, and vehicle hulls" },
    { "slug": "scout", "name": "Overpass Sniper", "cr": 0.5, "blurb": "watches the road from the collapsed span" },
    { "slug": "worg", "name": "Alpha Waste Hound", "cr": 0.5, "blurb": "cunning pack leader, holds grudges" },
    { "slug": "ghoul", "name": "Feral Cannibal", "cr": 1, "blurb": "paralytic bite, den full of bones" },
    { "slug": "dire-wolf", "name": "Mutant Alpha", "cr": 1, "blurb": "twice the wolf the old world knew" },
    { "slug": "specter", "name": "Echo of the Fall", "cr": 1, "blurb": "afterimage of the last day, still screaming" },
    { "slug": "giant-spider", "name": "Silo Spinner", "cr": 1, "blurb": "webs the missile silo stairwells" },
    { "slug": "animated-armor", "name": "Haywire Exo-Rig", "cr": 1, "blurb": "empty work-suit on a corrupted routine" },
    { "slug": "harpy", "name": "Screech Mutant", "cr": 1, "blurb": "winged horror nesting in the control tower" },
    { "slug": "bugbear", "name": "Overpass Troll", "cr": 1, "blurb": "ambushes from the underpass dark" },
    { "slug": "death-dog", "name": "Two-Headed Coyote", "cr": 1, "blurb": "desert mutant, filthy bite" },
    { "slug": "bandit-captain", "name": "Raid Boss", "cr": 2, "blurb": "runs the convoy raids from a war-truck" },
    { "slug": "berserker", "name": "Chem-Fiend", "cr": 2, "blurb": "combat stims, no off switch" },
    { "slug": "cult-fanatic", "name": "Atomic Priest", "cr": 2, "blurb": "blesses the faithful with the warm glow" },
    { "slug": "ogre", "name": "Muta-Hulk", "cr": 2, "blurb": "swollen strongman of the crater tribes" },
    { "slug": "mimic", "name": "Trapped Supply Crate", "cr": 2, "blurb": "the loot chews back" },
    { "slug": "will-o-wisp", "name": "Reactor Ghost", "cr": 2, "blurb": "drifting charge from the melted core" },
    { "slug": "gargoyle", "name": "Statue Sentinel", "cr": 2, "blurb": "monument that defends the dead plaza" },
    { "slug": "wererat", "name": "Sewer King's Agent", "cr": 2, "blurb": "spliced spy of the underground market" },
    { "slug": "ankheg", "name": "Acid Burrower", "cr": 2, "blurb": "erupts from the roadbed under vehicles" },
    { "slug": "ochre-jelly", "name": "Chem-Spill Mass", "cr": 2, "blurb": "living solvent from the tanker graveyard" },
    { "slug": "ghast", "name": "Pit Feeder", "cr": 2, "blurb": "reeking king of the corpse pits" },
    { "slug": "wight", "name": "Dead Commander", "cr": 3, "blurb": "still holding the line at the checkpoint" },
    { "slug": "hell-hound", "name": "Furnace Hound", "cr": 3, "blurb": "flame-vented beast of the burn zones" },
    { "slug": "werewolf", "name": "Moon-Howler", "cr": 3, "blurb": "settlement neighbor with a monthly problem" },
    { "slug": "winter-wolf", "name": "Nuclear-Winter Wolf", "cr": 3, "blurb": "white terror of the frozen latitudes" },
    { "slug": "minotaur", "name": "Maze Mutant", "cr": 3, "blurb": "claims the collapsed mall as territory" },
    { "slug": "veteran", "name": "Old-World Soldier", "cr": 3, "blurb": "the last professional in a world of amateurs" },
    { "slug": "phase-spider", "name": "Blink Stalker", "cr": 3, "blurb": "teleporting predator from the test site" },
    { "slug": "basilisk", "name": "Glass-Gaze Lizard", "cr": 3, "blurb": "its stare vitrifies flesh" },
    { "slug": "manticore", "name": "Spine-Launcher", "cr": 3, "blurb": "winged mutant that fires its own quills" },
    { "slug": "doppelganger", "name": "Skin-Taker", "cr": 3, "blurb": "wears the faces of the missing" },
    { "slug": "green-hag", "name": "Bog Witch", "cr": 3, "blurb": "trades clean water for terrible favors" },
    { "slug": "ettin", "name": "Fused Twins", "cr": 4, "blurb": "two heads arguing over one shotgun" },
    { "slug": "ghost", "name": "Vault Echo", "cr": 4, "blurb": "the shelter's last occupant never left" },
    { "slug": "black-pudding", "name": "Toxic Bloom", "cr": 4, "blurb": "spreading acid mass from the waste ponds" },
    { "slug": "chuul", "name": "Harbor Horror", "cr": 4, "blurb": "clawed thing grown huge in the drowned docks" },
    { "slug": "troll", "name": "Rad-Troll", "cr": 5, "blurb": "regenerates unless you burn it" },
    { "slug": "vampire-spawn", "name": "Blood Baron's Thrall", "cr": 5, "blurb": "trades blood like currency" },
    { "slug": "wraith", "name": "Ground-Zero Shade", "cr": 5, "blurb": "reaper haunting the blast crater" },
    { "slug": "flesh-golem", "name": "Lab-Stitched Brute", "cr": 5, "blurb": "pre-Fall experiment, still following orders" },
    { "slug": "fire-elemental", "name": "Living Firestorm", "cr": 5, "blurb": "self-sustaining blaze with intent" },
    { "slug": "earth-elemental", "name": "Rubble Walker", "cr": 5, "blurb": "animate collapse of concrete and rebar" },
    { "slug": "shambling-mound", "name": "Compost Colossus", "cr": 5, "blurb": "mutant greenery swallowing the suburbs" },
    { "slug": "bulette", "name": "Road Shark", "cr": 5, "blurb": "bursts through asphalt under convoys" },
    { "slug": "gladiator", "name": "Thunderdome Champion", "cr": 5, "blurb": "undefeated in the settlement pits" },
    { "slug": "otyugh", "name": "Dump Dweller", "cr": 5, "blurb": "tentacled king of the landfill" },
    { "slug": "medusa", "name": "Glass Widow", "cr": 6, "blurb": "her gaze finishes what the bombs started" },
    { "slug": "invisible-stalker", "name": "Camo-Field Assassin", "cr": 6, "blurb": "military cloaking unit, mission still active" },
    { "slug": "mage", "name": "Tech-Shaman", "cr": 6, "blurb": "coaxes miracles from old-world machines" },
    { "slug": "wyvern", "name": "Ridge Terror", "cr": 6, "blurb": "venom-tailed flyer nesting in the wind farms" },
    { "slug": "oni", "name": "Warlord of the Dunes", "cr": 7, "blurb": "giant chieftain who vanishes in sandstorms" },
    { "slug": "stone-giant", "name": "Quarry Titan", "cr": 7, "blurb": "hurls engine blocks like pebbles" },
    { "slug": "shield-guardian", "name": "Guardian Automaton", "cr": 7, "blurb": "pre-Fall bodyguard bound to a lost keycard" },
    { "slug": "assassin", "name": "Contract Ghost", "cr": 8, "blurb": "the settlements' quiet way of settling disputes" },
    { "slug": "frost-giant", "name": "Winter Warlord", "cr": 8, "blurb": "rules the frozen north in salvaged plate" },
    { "slug": "hydra", "name": "Chem-Hydra", "cr": 8, "blurb": "cut a head, the vats grew it back double" },
    { "slug": "tyrannosaurus-rex", "name": "Gene-Vault Rex", "cr": 8, "blurb": "someone reopened the wrong ark" },
    { "slug": "fire-giant", "name": "Foundry Tyrant", "cr": 9, "blurb": "reforges the old world into weapons" },
    { "slug": "clay-golem", "name": "Berserk Loader Mech", "cr": 9, "blurb": "cargo walker with corrupted safeties" },
    { "slug": "treant", "name": "Elder Overgrowth", "cr": 9, "blurb": "the forest that ate the city, walking" },
    { "slug": "stone-golem", "name": "Bunker Guardian", "cr": 10, "blurb": "immovable sentinel of the deep vault" },
    { "slug": "aboleth", "name": "The Reservoir Mind", "cr": 10, "blurb": "ancient thing awake in the flooded metro" },
    { "slug": "behir", "name": "Pipeline Serpent", "cr": 11, "blurb": "lightning-gutted beast coiled in the refinery" },
    { "slug": "efreeti", "name": "Reactor Djinn", "cr": 11, "blurb": "the meltdown given will and grievance" },
    { "slug": "archmage", "name": "The Vault Director", "cr": 12, "blurb": "pre-Fall mind running long experiments" },
    { "slug": "vampire", "name": "The Blood Baron", "cr": 13, "blurb": "owns the largest clean-blood bank in the wastes" },
    { "slug": "storm-giant", "name": "The Storm Caller", "cr": 13, "blurb": "titan who walks the radstorm fronts" },
    { "slug": "iron-golem", "name": "War Machine Prime", "cr": 16, "blurb": "the last tank the old world built" },
    { "slug": "purple-worm", "name": "The Deep Devourer", "cr": 15, "blurb": "what really collapsed the metro lines" },
    { "slug": "ancient-red-dragon", "name": "The Firestorm Engine", "cr": 24, "blurb": "wasteland legend; settlements mark its flights" }
  ]
}
